MANIFEST.in
__init__.py
readme.rst
setup.py
tweetup.py
tweetup_v1.3.egg-info/PKG-INFO
tweetup_v1.3.egg-info/SOURCES.txt
tweetup_v1.3.egg-info/dependency_links.txt
tweetup_v1.3.egg-info/requires.txt
tweetup_v1.3.egg-info/top_level.txt