Metadata-Version: 1.0
Name: tweetup-v1.3
Version: 1.2
Summary: Tweetup  module.
Home-page: https://github.com/anurag619/mywork/tree/master/tweet
Author: Anurag Kumar
Author-email: anurag3rdsep@gmail.com
License: MIT
Platform: Linux
